README.txt
setup.py
nestermike12345/nestermike12345.py
nestermike12345.egg-info/PKG-INFO
nestermike12345.egg-info/SOURCES.txt
nestermike12345.egg-info/dependency_links.txt
nestermike12345.egg-info/top_level.txt